LICENSE
MANIFEST.in
README.md
setup.py
lie2me/__init__.py
lie2me/exceptions.py
lie2me/field.py
lie2me/form.py
lie2me/parsers.py
lie2me.egg-info/PKG-INFO
lie2me.egg-info/SOURCES.txt
lie2me.egg-info/dependency_links.txt
lie2me.egg-info/entry_points.txt
lie2me.egg-info/top_level.txt
lie2me/fields/__init__.py
lie2me/fields/boolean.py
lie2me/fields/date.py
lie2me/fields/datetime.py
lie2me/fields/decimal.py
lie2me/fields/email.py
lie2me/fields/float.py
lie2me/fields/integer.py
lie2me/fields/list.py
lie2me/fields/password.py
lie2me/fields/text.py
lie2me/fields/time.py