Metadata-Version: 1.0
Name: lie2me
Version: 0.0.0
Summary: A python library to validate user input.
Home-page: https://github.com/hugollm/lie2me
Author: Hugo Leonardo Leão Mota
Author-email: hugo.txt@gmail.com
License: MIT
Keywords: form fields validation user input
Platform: UNKNOWN
